livedoc/__init__.py
livedoc/__main__.py
livedoc/about.py
livedoc/exceptions.py
livedoc/expressions.py
livedoc/processors.py
livedoc/reports.py
livedoc-0.3.4.dist-info/DESCRIPTION.rst
livedoc-0.3.4.dist-info/METADATA
livedoc-0.3.4.dist-info/RECORD
livedoc-0.3.4.dist-info/WHEEL
livedoc-0.3.4.dist-info/entry_points.txt
livedoc-0.3.4.dist-info/metadata.json
livedoc-0.3.4.dist-info/top_level.txt
